Metadata-Version: 2.1
Name: colorize-cli
Version: 0.1
Summary: Highlight matched strings in a text
Home-page: https://github.com/aleksandr-vin/colorize
Download-URL: https://github.com/aleksandr-vin/colorize/archive/v0.1.tar.gz
Author: Aleksandr Vinokurov
Author-email: aleksandr.vin@gmail.com
License: MIT
Keywords: cat,colors,terminal,console,logs,ascii,regex,cli
Platform: UNKNOWN
Classifier: Development Status :: 3 - Alpha
Classifier: Environment :: Console
Classifier: Intended Audience :: Developers
Classifier: Intended Audience :: End Users/Desktop
Classifier: Intended Audience :: Information Technology
Classifier: Topic :: Software Development
Classifier: Topic :: Home Automation
Classifier: Topic :: Internet
Classifier: Topic :: Scientific/Engineering :: Information Analysis
Classifier: Topic :: Software Development :: Libraries :: Python Modules
Classifier: Topic :: Software Development :: User Interfaces
Classifier: Topic :: System :: Monitoring
Classifier: Natural Language :: English
Classifier: License :: OSI Approved :: MIT License
Classifier: Programming Language :: Python :: 3
License-File: LICENSE.txt
